slatedb-0.10.0.dist-info/METADATA
slatedb-0.10.0.dist-info/WHEEL
slatedb.libs/libgcc_s-f5fcfe20.so.1
slatedb/__init__.py
slatedb/slatedb.cpython-310-i386-linux-gnu.so
slatedb/slatedb.pyi
slatedb-0.10.0.dist-info/RECORD
