Metadata-Version: 2.4
Name: slatedb
Version: 0.10.0
Classifier: Programming Language :: Rust
Classifier: Programming Language :: Python :: Implementation :: CPython
Classifier: Programming Language :: Python :: 3.10
Classifier: Programming Language :: Python :: 3.11
Classifier: Programming Language :: Python :: 3.12
Requires-Dist: pytest>=8.3 ; extra == 'test'
Requires-Dist: pytest-asyncio>=0.25.0 ; extra == 'test'
Requires-Dist: sphinx>=7.4 ; extra == 'docs'
Requires-Dist: sphinx-rtd-theme>=3.0 ; extra == 'docs'
Requires-Dist: sphinx-autoapi>=3.0 ; extra == 'docs'
Requires-Dist: ruff>=0.14.3 ; extra == 'lint'
Provides-Extra: test
Provides-Extra: docs
Provides-Extra: lint
Summary: A cloud native embedded storage engine built on object storage.
Home-Page: https://slatedb.io
Requires-Python: >=3.10
